taskbadger/__init__.py
taskbadger/celery.py
taskbadger/cli_main.py
taskbadger/config.py
taskbadger/decorators.py
taskbadger/exceptions.py
taskbadger/integrations.py
taskbadger/mug.py
taskbadger/process.py
taskbadger/safe_sdk.py
taskbadger/sdk.py
taskbadger/utils.py
taskbadger/cli/__init__.py
taskbadger/cli/basics.py
taskbadger/cli/list_tasks.py
taskbadger/cli/utils.py
taskbadger/cli/wrapper.py
taskbadger/internal/__init__.py
taskbadger/internal/client.py
taskbadger/internal/errors.py
taskbadger/internal/py.typed
taskbadger/internal/types.py
taskbadger/internal/api/__init__.py
taskbadger/internal/api/action_endpoints/__init__.py
taskbadger/internal/api/action_endpoints/action_cancel.py
taskbadger/internal/api/action_endpoints/action_create.py
taskbadger/internal/api/action_endpoints/action_get.py
taskbadger/internal/api/action_endpoints/action_list.py
taskbadger/internal/api/action_endpoints/action_partial_update.py
taskbadger/internal/api/action_endpoints/action_update.py
taskbadger/internal/api/task_endpoints/__init__.py
taskbadger/internal/api/task_endpoints/task_cancel.py
taskbadger/internal/api/task_endpoints/task_create.py
taskbadger/internal/api/task_endpoints/task_get.py
taskbadger/internal/api/task_endpoints/task_list.py
taskbadger/internal/api/task_endpoints/task_partial_update.py
taskbadger/internal/api/task_endpoints/task_update.py
taskbadger/internal/models/__init__.py
taskbadger/internal/models/action.py
taskbadger/internal/models/action_request.py
taskbadger/internal/models/paginated_task_list.py
taskbadger/internal/models/patched_action_request.py
taskbadger/internal/models/patched_task_request.py
taskbadger/internal/models/patched_task_request_tags.py
taskbadger/internal/models/status_enum.py
taskbadger/internal/models/task.py
taskbadger/internal/models/task_request.py
taskbadger/internal/models/task_request_tags.py
taskbadger/internal/models/task_tags.py
taskbadger/systems/__init__.py
taskbadger/systems/celery.py
taskbadger-1.6.2.dist-info/METADATA
taskbadger-1.6.2.dist-info/WHEEL
taskbadger-1.6.2.dist-info/entry_points.txt
taskbadger-1.6.2.dist-info/licenses/LICENSE
taskbadger-1.6.2.dist-info/RECORD
