Metadata-Version: 2.4
Name: taskbadger
Version: 1.6.2
Summary: The official Python SDK for Task Badger
Project-URL: Changelog, https://github.com/taskbadger/taskbadger-python/releases
Project-URL: homepage, https://taskbadger.net/
Project-URL: repository, https://github.com/taskbadger/taskbadger-python
Project-URL: documentation, https://docs.taskbadger.net/
License-File: LICENSE
Classifier: Development Status :: 4 - Beta
Classifier: Environment :: Web Environment
Classifier: Intended Audience :: Developers
Classifier: Operating System :: OS Independent
Classifier: Programming Language :: Python
Classifier: Programming Language :: Python :: 3.9
Classifier: Programming Language :: Python :: 3.10
Classifier: Programming Language :: Python :: 3.11
Classifier: Programming Language :: Python :: 3.12
Classifier: Topic :: Software Development :: Libraries :: Python Modules
Requires-Python: >=3.9
Requires-Dist: attrs>=21.3.0
Requires-Dist: httpx>=0.20.0
Requires-Dist: importlib-metadata>=1.0; python_version < '3.8'
Requires-Dist: python-dateutil>=2.8.0
Requires-Dist: tomlkit>=0.12.5
Requires-Dist: typer[all]<0.10.0
Requires-Dist: typing-extensions>=4.7.1; python_version <= '3.9'
Provides-Extra: celery
Requires-Dist: celery<6.0.0,>=4.0.0; extra == 'celery'
